aioemit/__init__.py
tests/__init__.py
tests/test_emitter.py
aioemit-0.0.1.dist-info/LICENSE
aioemit-0.0.1.dist-info/METADATA
aioemit-0.0.1.dist-info/WHEEL
aioemit-0.0.1.dist-info/top_level.txt
aioemit-0.0.1.dist-info/RECORD
