Metadata-Version: 2.1
Name: aioemit
Version: 0.0.1
Summary: A minimalistic async event bus implementation
Home-page: UNKNOWN
Author: iunary
Author-email: contact@yusuf.im
License: MIT License
Keywords: emitter,event bus,pubsub,async,subscribe,emit,publish,aioemit
Platform: UNKNOWN
Classifier: Development Status :: 5 - Production/Stable
Classifier: Intended Audience :: Developers
Classifier: License :: OSI Approved :: MIT License
Classifier: Programming Language :: Python :: 3
Classifier: Programming Language :: Python :: 3.8
License-File: LICENSE
